shortlink/__init__.py
shortlink/admin.py
shortlink/models.py
shortlink/settings.py
shortlink/urls.py
shortlink/utils.py
shortlink/views.py
shortlink/locale/fa/LC_MESSAGES/django.mo
shortlink/locale/fa/LC_MESSAGES/django.po
shortlink/migrations/0001_initial.py
shortlink/migrations/0002_auto_20200902_2012.py
shortlink/migrations/0003_auto_20200916_2241.py
shortlink/migrations/0004_auto_20200916_2242.py
shortlink/migrations/0005_auto_20200917_1707.py
shortlink/migrations/0006_auto_20201008_1614.py
shortlink/migrations/__init__.py
django_shortlink-0.0.8.dist-info/LICENSE
django_shortlink-0.0.8.dist-info/METADATA
django_shortlink-0.0.8.dist-info/WHEEL
django_shortlink-0.0.8.dist-info/top_level.txt
django_shortlink-0.0.8.dist-info/RECORD
