Metadata-Version: 2.1
Name: django-shortlink
Version: 0.0.8
Summary: A simple Django App to hold short links mapped to long urls used in your projects.
Home-page: https://github.com/Execut3/django-shortlink
Author: Execut3
Author-email: execut3.binarycodes@gmail.com
License: GPT
Platform: UNKNOWN
Requires-Dist: Django (>=2.0)
